herald/__init__.py
herald/herald.py
herald/notifiers/__init__.py
herald/notifiers/base.py
herald/notifiers/gmail.py
herald/notifiers/outlook.py
herald/notifiers/twilio.py
herald_notify-1.0.1.dist-info/DESCRIPTION.rst
herald_notify-1.0.1.dist-info/METADATA
herald_notify-1.0.1.dist-info/RECORD
herald_notify-1.0.1.dist-info/WHEEL
herald_notify-1.0.1.dist-info/metadata.json
herald_notify-1.0.1.dist-info/top_level.txt
