Metadata-Version: 2.0
Name: herald-notify
Version: 1.0.1
Summary: Programmable, extensible and easy to use notification system
Home-page: https://github.com/varunagrawal/herald
Author: Varun Agrawal
Author-email: varunagrawal@gatech.edu
License: MIT
Keywords: herald,notification,notify,extensible
Platform: any
Classifier: Development Status :: 5 - Production/Stable
Classifier: Environment :: Console
Classifier: Intended Audience :: Developers
Classifier: License :: OSI Approved :: BSD License
Classifier: Operating System :: POSIX
Classifier: Operating System :: MacOS
Classifier: Operating System :: Unix
Classifier: Operating System :: Microsoft :: Windows
Classifier: Programming Language :: Python
Classifier: Programming Language :: Python :: 2.7
Classifier: Programming Language :: Python :: 3.5
Classifier: Programming Language :: Python :: 3.6
Classifier: Topic :: Software Development :: Libraries :: Python Modules
Requires-Dist: google-api-python-client
Requires-Dist: httplib2
Requires-Dist: oauth2client
Requires-Dist: twilio
